sv_practise_distributions/Binomialdistribution.py
sv_practise_distributions/Gaussiandistribution.py
sv_practise_distributions/Generaldistribution.py
sv_practise_distributions/__init__.py
sv_practise_distributions-0.1.dist-info/DESCRIPTION.rst
sv_practise_distributions-0.1.dist-info/METADATA
sv_practise_distributions-0.1.dist-info/RECORD
sv_practise_distributions-0.1.dist-info/WHEEL
sv_practise_distributions-0.1.dist-info/metadata.json
sv_practise_distributions-0.1.dist-info/top_level.txt
