Metadata-Version: 2.0
Name: sv-practise-distributions
Version: 0.1
Summary: Gaussian & Binomial distributions
Home-page: UNKNOWN
Author: UNKNOWN
Author-email: UNKNOWN
License: UNKNOWN
Platform: UNKNOWN
